{
  "annotations": {
    "list": [
      {
        "builtIn": 1,
        "datasource": {
          "type": "grafana",
          "uid": "-- Grafana --"
        },
        "enable": true,
        "hide": true,
        "iconColor": "rgba(0, 211, 255, 1)",
        "name": "Annotations & Alerts",
        "type": "dashboard"
      }
    ]
  },
  "editable": true,
  "fiscalYearStartMonth": 0,
  "graphTooltip": 0,
  "id": null,
  "links": [],
  "liveNow": false,
  "panels": [
    {
      "datasource": {
        "type": "loki",
        "uid": "loki"
      },
      "gridPos": {
        "h": 12,
        "w": 24,
        "x": 0,
        "y": 0
      },
      "id": 1,
      "options": {
        "showTime": true,
        "showLabels": true,
        "showCommonLabels": false,
        "wrapLogMessage": true,
        "prettifyLogMessage": true,
        "enableLogDetails": true,
        "dedupStrategy": "none",
        "sortOrder": "Descending"
      },
      "targets": [
        {
          "datasource": {
            "type": "loki",
            "uid": "loki"
          },
          "editorMode": "code",
          "expr": "{job=\"symfony\"}",
          "queryType": "",
          "refId": "A"
        }
      ],
      "title": "Tous les Logs (Simple)",
      "type": "logs"
    },
    {
      "datasource": {
        "type": "loki",
        "uid": "loki"
      },
      "gridPos": {
        "h": 8,
        "w": 8,
        "x": 0,
        "y": 12
      },
      "id": 2,
      "options": {
        "colorMode": "value",
        "graphMode": "area",
        "justifyMode": "auto",
        "orientation": "auto",
        "reduceOptions": {
          "calcs": [
            "lastNotNull"
          ],
          "fields": "",
          "values": false
        },
        "textMode": "auto"
      },
      "pluginVersion": "10.4.0",
      "targets": [
        {
          "datasource": {
            "type": "loki",
            "uid": "loki"
          },
          "editorMode": "code",
          "expr": "count_over_time({job=\"symfony\"}[1h])",
          "queryType": "",
          "refId": "A"
        }
      ],
      "title": "Total Logs (1h)",
      "type": "stat"
    },
    {
      "datasource": {
        "type": "loki",
        "uid": "loki"
      },
      "gridPos": {
        "h": 8,
        "w": 8,
        "x": 8,
        "y": 12
      },
      "id": 3,
      "options": {
        "colorMode": "value",
        "graphMode": "area",
        "justifyMode": "auto",
        "orientation": "auto",
        "reduceOptions": {
          "calcs": [
            "lastNotNull"
          ],
          "fields": "",
          "values": false
        },
        "textMode": "auto"
      },
      "pluginVersion": "10.4.0",
      "targets": [
        {
          "datasource": {
            "type": "loki",
            "uid": "loki"
          },
          "editorMode": "code",
          "expr": "count_over_time({job=\"symfony\", channel=\"signals\"}[1h])",
          "queryType": "",
          "refId": "A"
        }
      ],
      "title": "Logs Signaux (1h)",
      "type": "stat"
    },
    {
      "datasource": {
        "type": "loki",
        "uid": "loki"
      },
      "gridPos": {
        "h": 8,
        "w": 8,
        "x": 16,
        "y": 12
      },
      "id": 4,
      "options": {
        "colorMode": "value",
        "graphMode": "area",
        "justifyMode": "auto",
        "orientation": "auto",
        "reduceOptions": {
          "calcs": [
            "lastNotNull"
          ],
          "fields": "",
          "values": false
        },
        "textMode": "auto"
      },
      "pluginVersion": "10.4.0",
      "targets": [
        {
          "datasource": {
            "type": "loki",
            "uid": "loki"
          },
          "editorMode": "code",
          "expr": "count_over_time({job=\"symfony\", level=\"info\"}[1h])",
          "queryType": "",
          "refId": "A"
        }
      ],
      "title": "Logs INFO (1h)",
      "type": "stat"
    },
    {
      "datasource": {
        "type": "loki",
        "uid": "loki"
      },
      "gridPos": {
        "h": 8,
        "w": 12,
        "x": 0,
        "y": 20
      },
      "id": 5,
      "options": {
        "showTime": true,
        "showLabels": true,
        "showCommonLabels": false,
        "wrapLogMessage": true,
        "prettifyLogMessage": true,
        "enableLogDetails": true,
        "dedupStrategy": "none",
        "sortOrder": "Descending"
      },
      "targets": [
        {
          "datasource": {
            "type": "loki",
            "uid": "loki"
          },
          "editorMode": "code",
          "expr": "{job=\"symfony\", channel=\"signals\"}",
          "queryType": "",
          "refId": "A"
        }
      ],
      "title": "Logs de Signaux",
      "type": "logs"
    },
    {
      "datasource": {
        "type": "loki",
        "uid": "loki"
      },
      "gridPos": {
        "h": 8,
        "w": 12,
        "x": 12,
        "y": 20
      },
      "id": 6,
      "options": {
        "showTime": true,
        "showLabels": true,
        "showCommonLabels": false,
        "wrapLogMessage": true,
        "prettifyLogMessage": true,
        "enableLogDetails": true,
        "dedupStrategy": "none",
        "sortOrder": "Descending"
      },
      "targets": [
        {
          "datasource": {
            "type": "loki",
            "uid": "loki"
          },
          "editorMode": "code",
          "expr": "{job=\"symfony\", level=\"info\"}",
          "queryType": "",
          "refId": "A"
        }
      ],
      "title": "Logs INFO",
      "type": "logs"
    }
  ],
  "refresh": "5s",
  "schemaVersion": 38,
  "style": "dark",
  "tags": [
    "trading",
    "logs",
    "simple"
  ],
  "templating": {
    "list": []
  },
  "time": {
    "from": "now-2h",
    "to": "now"
  },
  "timepicker": {},
  "timezone": "",
  "title": "Dashboard Logs Simple",
  "uid": "simple-logs",
  "version": 1,
  "weekStart": ""
}
